pvyzmgs-1.0.1.dist-info/METADATA
pvyzmgs-1.0.1.dist-info/WHEEL
pvyzmgs-1.0.1.dist-info/licenses/LICENSE
pvyzmgs/__init__.py
pvyzmgs/animation.py
pvyzmgs/data.py
pvyzmgs/plotting.py
pvyzmgs/resampling.py
pvyzmgs/simulation.py
pvyzmgs-1.0.1.dist-info/RECORD
